pr_checker/__init__.py
pr_checker/cli.py
pr_checker-0.2.dist-info/METADATA
pr_checker-0.2.dist-info/WHEEL
pr_checker-0.2.dist-info/entry_points.txt
pr_checker-0.2.dist-info/top_level.txt
pr_checker-0.2.dist-info/RECORD
