Metadata-Version: 2.1
Name: pr_checker
Version: 0.2
Summary: A simple CLI tool to check PR statuses on GitHub
Home-page: https://github.com/raquelmsmith/pr_checker
Author: Raquel M Smith
Author-email: hello@raquelmsmith.com
Project-URL: Homepage, https://github.com/raquelmsmith/pr_checker
Classifier: Programming Language :: Python :: 3
Classifier: License :: OSI Approved :: MIT License
Classifier: Operating System :: OS Independent
Requires-Python: >=3.6
Requires-Dist: requests
